magicwall/Dockerfile
magicwall/__init__.py
magicwall/common.py
magicwall/magicwall_api.py
magicwall/server.py
magicwall/static/DragDropTouch.js
magicwall/static/hilite-solarized-light.css
magicwall/static/magicwall.css
magicwall/static/magicwall.js
magicwall/static/unknown.png
magicwall/templates/magicwall.html
magicwall/utils.py
magicwall-0.0.3.dist-info/METADATA
magicwall-0.0.3.dist-info/WHEEL
magicwall-0.0.3.dist-info/entry_points.txt
magicwall-0.0.3.dist-info/RECORD
