Metadata-Version: 2.1
Name: magicwall
Version: 0.0.3
Summary: This is the magic wall (magicwall.io)
Home-page: https://projects.om-office.de/frans/magicwall.io
Author: Frans Fürst
Author-email: frans.fuerst+gitlab@protonmail.com
Requires-Python: >=3.9,<4.0
Classifier: Programming Language :: Python :: 3
Classifier: Programming Language :: Python :: 3.9
Classifier: Programming Language :: Python :: 3.10
Classifier: Programming Language :: Python :: 3.11
Requires-Dist: asyncinotify (>=4.0.1,<5.0.0)
Requires-Dist: exifread (>=3.0.0,<4.0.0)
Requires-Dist: markdown (>=3.4.3,<4.0.0)
Requires-Dist: markdown-checklist (>=0.4.4,<0.5.0)
Requires-Dist: pillow (>=9.5.0,<10.0.0)
Requires-Dist: pyyaml (>=6.0,<7.0)
Requires-Dist: quart (>=0.18.4,<0.19.0)
Project-URL: Repository, https://projects.om-office.de/frans/magicwall.io
